cuquantum/__init__.py
cuquantum/__main__.py
cuquantum/_version.py
cuquantum/_internal/__init__.py
cuquantum/_internal/enum_utils.py
cuquantum/_internal/formatters.py
cuquantum/_internal/mem_limit.py
cuquantum/_internal/package_ifc.py
cuquantum/_internal/package_ifc_cupy.py
cuquantum/_internal/package_ifc_torch.py
cuquantum/_internal/package_wrapper.py
cuquantum/_internal/tensor_ifc.py
cuquantum/_internal/tensor_ifc_cupy.py
cuquantum/_internal/tensor_ifc_numpy.py
cuquantum/_internal/tensor_ifc_torch.py
cuquantum/_internal/tensor_wrapper.py
cuquantum/_internal/typemaps.py
cuquantum/_internal/utils.py
cuquantum/bindings/__init__.pxd
cuquantum/bindings/__init__.py
cuquantum/bindings/_utils.cpython-313-x86_64-linux-gnu.so
cuquantum/bindings/_utils.pxd
cuquantum/bindings/_utils.pyx
cuquantum/bindings/cudensitymat.cpython-313-x86_64-linux-gnu.so
cuquantum/bindings/cudensitymat.pxd
cuquantum/bindings/cudensitymat.pyx
cuquantum/bindings/custatevec.cpython-313-x86_64-linux-gnu.so
cuquantum/bindings/custatevec.pxd
cuquantum/bindings/custatevec.pyx
cuquantum/bindings/cutensornet.cpython-313-x86_64-linux-gnu.so
cuquantum/bindings/cutensornet.pxd
cuquantum/bindings/cutensornet.pyx
cuquantum/bindings/cycudensitymat.cpython-313-x86_64-linux-gnu.so
cuquantum/bindings/cycudensitymat.pxd
cuquantum/bindings/cycudensitymat.pyx
cuquantum/bindings/cycustatevec.cpython-313-x86_64-linux-gnu.so
cuquantum/bindings/cycustatevec.pxd
cuquantum/bindings/cycustatevec.pyx
cuquantum/bindings/cycutensornet.cpython-313-x86_64-linux-gnu.so
cuquantum/bindings/cycutensornet.pxd
cuquantum/bindings/cycutensornet.pyx
cuquantum/bindings/_internal/cudensitymat.cpython-313-x86_64-linux-gnu.so
cuquantum/bindings/_internal/custatevec.cpython-313-x86_64-linux-gnu.so
cuquantum/bindings/_internal/cutensornet.cpython-313-x86_64-linux-gnu.so
cuquantum/custatevec/__init__.py
cuquantum/cutensornet/__init__.py
cuquantum/cutensornet/experimental.py
cuquantum/cutensornet/tensor.py
cuquantum/densitymat/__init__.py
cuquantum_python_cu11-25.6.0.dist-info/licenses/LICENSE
cuquantum_python_cu11-25.6.0.dist-info/METADATA
cuquantum_python_cu11-25.6.0.dist-info/WHEEL
cuquantum_python_cu11-25.6.0.dist-info/top_level.txt
cuquantum_python_cu11-25.6.0.dist-info/RECORD
