Metadata-Version: 2.4
Name: cuquantum-python-cu11
Version: 25.6.0
Summary: NVIDIA cuQuantum Python
Home-page: https://developer.nvidia.com/cuquantum-sdk
Author: NVIDIA Corporation
Author-email: cuquantum-python@nvidia.com
License: BSD-3-Clause
Project-URL: Bug Tracker, https://github.com/NVIDIA/cuQuantum/issues
Project-URL: User Forum, https://github.com/NVIDIA/cuQuantum/discussions
Project-URL: Documentation, https://docs.nvidia.com/cuda/cuquantum/latest/python/
Project-URL: Source Code, https://github.com/NVIDIA/cuQuantum
Classifier: Development Status :: 5 - Production/Stable
Classifier: Operating System :: POSIX :: Linux
Classifier: Topic :: Education
Classifier: Topic :: Scientific/Engineering
Classifier: Programming Language :: Python :: 3 :: Only
Classifier: Programming Language :: Python :: 3.11
Classifier: Programming Language :: Python :: 3.12
Classifier: Programming Language :: Python :: 3.13
Classifier: Programming Language :: Python :: Implementation :: CPython
Classifier: Environment :: GPU :: NVIDIA CUDA
Classifier: Environment :: GPU :: NVIDIA CUDA :: 11
Requires-Python: >=3.11
License-File: LICENSE
Requires-Dist: numpy<3.0,>=1.21
Requires-Dist: custatevec-cu11~=1.9
Requires-Dist: cutensornet-cu11~=2.8
Requires-Dist: cudensitymat-cu11~=0.2
Requires-Dist: cupy-cuda11x>=13.0
Provides-Extra: test
Requires-Dist: pytest>=6.2; extra == "test"
Requires-Dist: pytest-xdist; extra == "test"
Requires-Dist: opt_einsum; extra == "test"
Requires-Dist: cffi>=1.0.0; extra == "test"
Requires-Dist: nbformat; extra == "test"
Requires-Dist: nbconvert; extra == "test"
Requires-Dist: cirq-core; extra == "test"
Requires-Dist: qiskit<3,>=1.4.2; extra == "test"
Requires-Dist: qiskit-aer; extra == "test"
Requires-Dist: pylatexenc; extra == "test"
Requires-Dist: jsonschema==4.17.3; extra == "test"
Requires-Dist: networkx; extra == "test"
Requires-Dist: mpi4py; extra == "test"
Dynamic: author
Dynamic: author-email
Dynamic: classifier
Dynamic: description
Dynamic: description-content-type
Dynamic: home-page
Dynamic: license
Dynamic: license-file
Dynamic: project-url
Dynamic: provides-extra
Dynamic: requires-dist
Dynamic: requires-python
Dynamic: summary
